{"f0": "PAN Number", "f1": "Employer Name1", "f2": "Employer Name2", "f3": "Employer Name3", "f4": "Employer Name4", "f5": "Employer Address1", "f6": "Employer Address2", "f7": "Employer Address3", "f8": "Employer Address4", "f9": "Organization Contact Number1", "f10": "Organization Contact Number2", "f11": "Organization Contact Number3", "f12": "Organization Contact Number4", "f13": "Employee Designation1", "f14": "Employee Designation2", "f15": "Employee Designation3", "f16": "Employee Designation4", "f17": "Annual Income1", "f18": "Annual Income2", "f19": "Annual Income3", "f20": "Annual Income4", "f21": "Other Sources of income", "f22": "Purpose of account", "f23": "Maximum amount per transaction", "f25": "Any other account", "f26": "Estimated Monthly Transaction in number1", "f27": "Estimated Monthly Transaction in amount1", "f29": "Estimated Annual Transaction in number", "f30": "Estimated Annual Transaction in amount", "f31": "other_bank_name1", "f32": "other_bank_name2", "f33": "type_of_account1", "f34": "type_of_account2", "f35": "Beneficial Owner1", "f36": "Beneficial Owner1 Relation", "f37": "Beneficial Owner1 Address", "f38": "Beneficial Owner1 number", "f39": "Beneficial Owner2", "f40": "Beneficial Owner2 Relation", "f41": "Beneficial Owner2 Address", "f42": "Beneficial Owner2 number","f45": "Father Name of Nominee", "f46": "Grandfather Name of Nominee", "f47": "Nominee Name", "f48": "Nominee relation", "f49": "Nominee date of birth", "f50": "Nominee Address", "f51": "Identification document number of Nominee", "f52": "Identification document issue date"}